ownlayer/__init__.py
ownlayer/anthropic.py
ownlayer/calculate_cost.py
ownlayer/openai.py
ownlayer/ownlayer_api.py
ownlayer/utils.py
ownlayer-0.3.0.dist-info/LICENSE
ownlayer-0.3.0.dist-info/METADATA
ownlayer-0.3.0.dist-info/WHEEL
ownlayer-0.3.0.dist-info/RECORD
