Metadata-Version: 2.1
Name: ownlayer
Version: 0.3.0
Summary: Ownlayer Python SDK
Author: Diego Sisto
Author-email: diego@ownlayer.com
Requires-Python: >=3.12,<4.0
Classifier: Programming Language :: Python :: 3
Classifier: Programming Language :: Python :: 3.12
Provides-Extra: anthropic
Provides-Extra: openai
Requires-Dist: anthropic (>=0.34.0,<0.35.0) ; extra == "anthropic"
Requires-Dist: datetime (>=5.5,<6.0)
Requires-Dist: openai (>=1.37.2,<2.0.0) ; extra == "openai"
Requires-Dist: pydantic (>=2.8.2,<3.0.0)
Requires-Dist: python-dotenv (>=1.0.1,<2.0.0)
Requires-Dist: requests (>=2.32.3,<3.0.0)
Requires-Dist: wrapt (>=1.16.0,<2.0.0)
